{"page 123":["Proceed"],"page 122":["Proceed"],"page 125":["Try to operate the vehicle","Decide not to risk it and continue searching for another way out"],"page 127":["End Game and Leave Comments"],"page 129":["Land at this island","Ignore it and keep going"],"page 128":["Say the word “Fljght”","Try to pull the sword out of the mutant’s body first"],"page 77":["Proceed"],"page 76":["Ask her about the falling of the islands"],"page 79":["Proceed"],"page 78":["Take a closer look at the sight on the horizon"],"page 71":["Ask her about this airship","Ask her about the people on board","Ask her about the Gahl\u0027vuhr Sehn","Ask her about what happened to you","Ask her about the falling of the islands"],"page 70":["Follow the woman"],"page 73":["Ask her about the falling of the islands"],"page 72":["Proceed"],"page 75":["Ask her about the falling of the islands"],"page 74":["Ask her about the falling of the islands"],"page 132":["Proceed"],"page 131":["Proceed"],"page 112":["End Game and Leave Comments"],"page 111":["Push the button which says “Jgnjtjpn”","Push the button which says “Sflf-dfstrvct”"],"page 113":["Twist the sword inside the mutant’s gut","Drive your weapon deeper into its body"],"page 115":["Hide in one of the cabins","Look for a way to get off the airship"],"page 118":["Proceed"],"page 117":["Try to operate the vehicle","Decide not to risk it and continue searching for another way out"],"page 88":["Push the captain out of the way","Turn away and worry about yourself instead"],"page 87":["Hide in one of the cabins","Look for a way to get off the airship"],"page 119":["End Game and Leave Comments"],"page 89":["Hide in one of the cabins","Look for a way to get off the airship"],"page 80":["Proceed"],"page 82":["Proceed"],"page 81":["Proceed"],"page 84":["Stay on the upper deck and help the mercenaries","Retreat into the cabins below deck"],"page 83":["Follow her up to the balcony"],"page 86":["Retreat into the cabins below after all","Stubbornly remain here and try to help the mercenaries"],"page 85":["Stay on the upper deck, ready to help","Retreat into the cabins below deck"],"page 121":["Disembark onto this new island, leaving the captain behind","Stay with the drifting ship"],"page 6":["Stay against the wall","Try to move to a different location"],"page 19":["Proceed"],"page 5":["Proceed"],"page 18":["Proceed"],"page 144":["Land at this new island","Ignore it and keep going"],"page 8":["Proceed"],"page 147":["End Game and Leave Comments"],"page 7":["Brace yourself against the wall","Try to move to a different location"],"page 146":["Proceed"],"page 2":["Keep your head down and seek shelter within the wall","Pick up some of the fragments of wood"],"page 149":["Proceed"],"page 1":["Crawl towards the ruins of your house nearby","Call out to your neighbours for aid","Inch your way towards one of the few houses still standing","Maintain your current position and hold on for dear life"],"page 148":["Come aboard as he requests","Drive as far away from this cannibal as you possibly can"],"page 4":["Proceed"],"page 3":["Proceed"],"page 11":["Proceed"],"page 99":["End Game and Leave Comments"],"page 10":["Proceed"],"page 98":["Proceed"],"page 13":["Proceed"],"page 12":["Call out to your neighbours for aid","Inch your way towards one of the few houses still standing","Maintain your current position and hold on for dear life"],"page 15":["Proceed"],"page 9":["Proceed"],"page 14":["Call out to your neighbours for aid","Inch your way towards one of the few houses still standing","Maintain your current position and hold on for dear life"],"page 17":["Proceed"],"page 16":["Proceed"],"page 91":["Attack the giant shambling mutant","Take on the smaller, weak-looking mutant","Decide not to risk it and run away from both of them"],"page 90":["Hide in one of the cabins","Look for a way to get off the airship"],"page 93":["Try to operate the vehicle","Decide not to risk it and continue searching for another way out"],"page 92":["Dash out into the corridor to initiate a surprise attack on the mutants","Remain in your hiding place, hoping that they do not find you"],"page 95":["Stay on this part of the ship with the captain","Cross over to the other part of the ship where Mother Ghared is, which is plummeting towards the ground"],"page 94":["Stay on this part of the ship with the captain","Cross over to the other part of the ship where Mother Ghared is, which is plummeting towards the ground"],"page 97":["Try to operate the vehicle","Decide not to risk it and continue searching for another way out"],"page 96":["Continue hiding here in the hope that the storm will pass","Move out of your hiding place as it’s no longer safe here"],"page 150":["Agree to join them","Refuse"],"page 152":["End Game and Leave Comments"],"page 151":["End Game and Leave Comments"],"page 154":["Proceed"],"page 153":["End Game and Leave Comments"],"page 134":["Land at this new island","Ignore it and keep going"],"page 29":["Go left where the wind is coming from","Head right to follow the voices"],"page 133":["Land at this new island","Ignore it and keep going"],"page 136":["Proceed"],"page 138":["Tell him you are from the Gahl’vuhr Sehn","Deny that you have anything to do with the Gahl’vuhr Sehn"],"page 137":["End Game and Leave Comments"],"page 139":["Approach the airship","Ignore it and keep going"],"page 22":["Inspect the mutant further","Ignore the mutant and leave the bedroom to find out where you are"],"page 21":["Poke the mutant with a stick","Search the room for valuables","Ignore the mutant and leave the bedroom to find out where you are"],"page 24":["Poke the mutant again","Ignore the mutant and leave the bedroom to find out where you are"],"page 23":["Go left where the wind is coming from","Head right to follow the voices"],"page 26":["Inspect the mutant further","Ignore the mutant and leave the bedroom to find out where you are"],"page 25":["Prepare to fight the mutant","Run out of the room"],"page 28":["Poke the mutant with a stick","Ignore the mutant and leave the bedroom to find out where you are"],"page 27":["Go left where the wind is coming from","Head right to follow the voices"],"page 20":["Inspect the mutant further","Search the room for valuables","Ignore the mutant and leave the bedroom to find out where you are"],"page 0":["Proceed"],"page 141":["Hide in the captain’s room until the mist passes","Stay up on deck to see what happens"],"page 140":["Approach the lake","Ignore the lake and decide to settle here upon this island"],"page 143":["Proceed"],"page 142":["Tell him your story","Make something up"],"page 167":["Proceed"],"page 166":["End Game and Leave Comments"],"page 33":["Inspect the mutant further","Ignore the mutant and leave the bedroom to find out where you are"],"page 32":["Prepare to fight the mutant","Run out of the room"],"page 35":["Go after the mutant","Wait for it to leave"],"page 34":["Go left where the wind is coming from","Head right to follow the voices"],"page 37":["Proceed"],"page 36":["Follow the mutant to the left","Head right instead","Stay where you are and call for help"],"page 39":["Follow the mercenary"],"page 38":["Proceed"],"page 31":["Nod your head in answer","Shake your head","Look at him blankly in response"],"page 30":["Follow the woman","Decide not to and go back downstairs"],"page 172":["End Game and Leave Comments"],"page 171":["End Game and Leave Comments"],"page 173":["End Game and Leave Comments"],"page 176":["End Game and Leave Comments"],"page 175":["End Game and Leave Comments"],"page 156":["Proceed"],"page 155":["Proceed"],"page 158":["Proceed"],"page 157":["Proceed"],"page 159":["Proceed"],"page 44":["Proceed"],"page 43":["Chase the mutant to the left","Decide not to pursue it and head right to the source of the voices"],"page 46":["Nod your head in answer","Shake your head","Look at him blankly in response"],"page 45":["Follow the woman"],"page 48":["Nod your head in answer","Shake your head","Look at him blankly in response"],"page 47":["Chase the mutant to the left","Decide not to pursue it and head right to the source of the voices"],"page 49":["Proceed"],"page 40":["Follow the mercenary"],"page 42":["Proceed"],"page 41":["Follow the mercenary"],"page 161":["Approach the airship","Ignore it and keep going"],"page 160":["Proceed"],"page 163":["Allow him to ride on the back of your vehicle","Refuse and drive away from here as quickly as you can"],"page 165":["End Game and Leave Comments"],"page 164":["Proceed"],"page 101":["End Game and Leave Comments"],"page 189":["End Game and Leave Comments"],"page 100":["Proceed"],"page 103":["Push the button which says “Jgnjtjpn”","Push the button which says “Sflf-dfstrvct”"],"page 102":["Proceed"],"page 105":["Proceed"],"page 104":["End Game and Leave Comments"],"page 107":["Proceed"],"page 106":["Say the word “Fljght”","Say “Fljght, Fljght”"],"page 55":["Proceed"],"page 109":["End Game and Leave Comments"],"page 108":["Say the word “Fljght”","Say “Fljght, Fljght”"],"page 57":["Proceed"],"page 56":["Agree to follow him after all","Leave this room and take the left fork of the corridor, towards the wind"],"page 59":["Proceed"],"page 58":["Agree to follow him after all","Leave this room and take the left fork of the corridor, towards the wind"],"page 51":["Nod your head in answer","Shake your head","Look at him blankly in response"],"page 50":["Ask her about this airship","Ask her about the people on board","Ask her about the Gahl\u0027vuhr Sehn","Ask her about what happened to you","Ask her about the falling of the islands"],"page 53":["Agree to follow him after all","Leave this room and take the left fork of the corridor, towards the wind"],"page 190":["End Game and Leave Comments"],"page 52":["Proceed"],"page 110":["Proceed"],"page 178":["Proceed"],"page 177":["Proceed"],"page 179":["Proceed"],"page 66":["Proceed"],"page 65":["Proceed"],"page 68":["Ask her about this airship","Ask her about the people on board","Ask her about the Gahl\u0027vuhr Sehn","Ask her about what happened to you","Ask her about the falling of the islands"],"page 67":["Follow her up to the balcony"],"page 69":["Proceed"],"page 60":["Proceed"],"page 62":["Proceed"],"page 61":["Nod your head in answer","Shake your head","Look at him blankly in response"],"page 64":["Proceed"],"page 63":["Proceed"],"page 180":["Proceed"],"page 183":["End Game and Leave Comments"]}